skqfit/__init__.py
skqfit/asmjacp.py
skqfit/qspectre.py
skqfit/skeleton.py
Scikit_Qfit-0.1.5.dist-info/AUTHORS.rst
Scikit_Qfit-0.1.5.dist-info/LICENSE.txt
Scikit_Qfit-0.1.5.dist-info/METADATA
Scikit_Qfit-0.1.5.dist-info/WHEEL
Scikit_Qfit-0.1.5.dist-info/top_level.txt
Scikit_Qfit-0.1.5.dist-info/RECORD
