Metadata-Version: 2.1
Name: Scikit-Qfit
Version: 0.1.5
Summary: Fit gradient orthogonal Q-polynomials to 2D data
Home-page: http://github.com/npdata/Scikit-qfit
Author: Geish Miladinovic
Author-email: npdata@bigpond.com
License: mit
Project-URL: Documentation, https://pyscaffold.org/
Platform: any
Classifier: Development Status :: 4 - Beta
Classifier: Programming Language :: Python
Classifier: License :: OSI Approved :: MIT License
Classifier: Intended Audience :: Science/Research
Classifier: Topic :: Scientific/Engineering
Classifier: Topic :: Scientific/Engineering :: Physics
Provides-Extra: testing
Requires-Dist: pytest ; extra == 'testing'
Requires-Dist: pytest-cov ; extra == 'testing'
